<annotation>
	<folder>potholes</folder>
	<filename>22.jpg</filename>
	<path>M:\PHD_Github\Dataset\train\potholes\22.jpg</path>
	<source>
		<database>Unknown</database>
	</source>
	<size>
		<width>526</width>
		<height>349</height>
		<depth>3</depth>
	</size>
	<segmented>0</segmented>
	<object>
		<name>pothole</name>
		<pose>Unspecified</pose>
		<truncated>0</truncated>
		<difficult>0</difficult>
		<bndbox>
			<xmin>124</xmin>
			<ymin>125</ymin>
			<xmax>311</xmax>
			<ymax>201</ymax>
		</bndbox>
	</object>
	<object>
		<name>pothole</name>
		<pose>Unspecified</pose>
		<truncated>0</truncated>
		<difficult>0</difficult>
		<bndbox>
			<xmin>281</xmin>
			<ymin>209</ymin>
			<xmax>462</xmax>
			<ymax>301</ymax>
		</bndbox>
	</object>
</annotation>
